{"cameraMode":{"drawMode":0,"name":"Shaded","section":"Shading Mode"},"sceneLighting":true,"audioPlay":false,"sceneViewState":{"m_AlwaysRefresh":false,"showFog":true,"showSkybox":true,"showFlares":true,"showImageEffects":true,"showParticleSystems":true,"showVisualEffectGraphs":true,"m_FxEnabled":true},"in2DMode":false,"pivot":{"x":-9.202641487121582,"y":5.084621429443359,"z":-3.4095051288604738},"rotation":{"x":0.16401930153369904,"y":0.42900311946868899,"z":-0.07953264564275742,"w":0.8847225904464722},"size":1.227500557899475,"orthographic":false}